LICENSE
MANIFEST.in
README.md
setup.py
django_sassy_coffee.egg-info/PKG-INFO
django_sassy_coffee.egg-info/SOURCES.txt
django_sassy_coffee.egg-info/dependency_links.txt
django_sassy_coffee.egg-info/requires.txt
django_sassy_coffee.egg-info/top_level.txt
sassy_coffee/__init__.py
sassy_coffee/compilers.py
sassy_coffee/utils.py
sassy_coffee/templatetags/__init__.py
sassy_coffee/templatetags/sassy_coffee.py
tests/__init__.py
tests/manage.py
tests/settings.py
tests/tests.py