Metadata-Version: 1.1
Name: django-sassy-coffee
Version: 0.1.1
Summary: This is a django application to compile SASS, SCSS and CoffeeScript files from the static directory into CSS and JavaScript files
Home-page: https://github.com/lmanzurv/sassy_coffee
Author: Laura Manzur
Author-email: lc.manzur@novcat.com.co
License: Apache License
Download-URL: https://github.com/lmanzurv/sassy_coffee
Keywords: sass coffeescript scss django
Platform: UNKNOWN
Classifier: Framework :: Django
Classifier: License :: OSI Approved :: Academic Free License (AFL)
Classifier: Natural Language :: English
Classifier: Programming Language :: Python :: 2.7
